mopidy_cranberry-0.1.0rc5.data/data/mopidy_cranberry/static/assets/cranberry-07c34050a151465c.js
mopidy_cranberry-0.1.0rc5.data/data/mopidy_cranberry/static/assets/cranberry-07c34050a151465c.js.br
mopidy_cranberry-0.1.0rc5.data/data/mopidy_cranberry/static/assets/cranberry_bg-d8f10fe2e51a7dfd.wasm
mopidy_cranberry-0.1.0rc5.data/data/mopidy_cranberry/static/assets/cranberry_bg-d8f10fe2e51a7dfd.wasm.br
mopidy_cranberry-0.1.0rc5.data/data/mopidy_cranberry/static/assets/favicon-bfb713af738cc967.ico
mopidy_cranberry-0.1.0rc5.data/data/mopidy_cranberry/static/assets/favicon-bfb713af738cc967.ico.br
mopidy_cranberry-0.1.0rc5.data/data/mopidy_cranberry/static/assets/main-075098a3a94b0a31.css
mopidy_cranberry-0.1.0rc5.data/data/mopidy_cranberry/static/assets/main-075098a3a94b0a31.css.br
mopidy_cranberry-0.1.0rc5.data/data/mopidy_cranberry/static/assets/mopidy_favicon-32x32-d63520fbf6d1f0fe.png
mopidy_cranberry-0.1.0rc5.data/data/mopidy_cranberry/static/assets/mopidy_favicon-32x32-d63520fbf6d1f0fe.png.br
mopidy_cranberry-0.1.0rc5.data/data/mopidy_cranberry/static/index.html
mopidy_cranberry-0.1.0rc5.dist-info/METADATA
mopidy_cranberry-0.1.0rc5.dist-info/WHEEL
mopidy_cranberry-0.1.0rc5.dist-info/entry_points.txt
mopidy_cranberry-0.1.0rc5.dist-info/licenses/LICENSE
mopidy_cranberry/__init__.py
mopidy_cranberry/core.py
mopidy_cranberry/ext.conf
mopidy_cranberry/frontend.py
mopidy_cranberry/mem.py
mopidy_cranberry-0.1.0rc5.dist-info/RECORD
